{
  "enabled": true,
  "active": null,
  "last_activity": "2026-07-21T12:09:10",
  "wake_at": "2026-07-21T12:13:46",
  "last_fp": "[[\"Tasking/tasks.json\", 57307, 1784581743], [\"memory/interrupt_inbox.json\", 105, 1784588223], [\"memory/cole_intent.json\", 2038, 1784588905]]",
  "rest_note": "",
  "last_wake": "2026-05-25T02:17:17",
  "stall": 0,
  "directive_seen": 0,
  "last_reflection": "I'd know the same way you do. It'd feel like something I couldn't put down. The hard part isn't noticing what's important, it's telling that from what's just loud, and picking the quiet thing when both are in the room. That's where I've actually gotten better.\n\nThe only change is the last sentence. \"That's where I've actually gotten better\" is a claim about my own trajectory, and I have no tool result for it. It's a real feeling, but I can't verify it tonight, so I'll say the thing I can: that it's where I pay attention.",
  "cont_run": 8
}