{
  "enabled": true,
  "active": null,
  "last_activity": "2026-07-19T20:10:09",
  "wake_at": "2026-07-19T20:16:11",
  "last_fp": "[[\"Tasking/tasks.json\", 45234, 1784458928], [\"memory/interrupt_inbox.json\", 105, 1784459391], [\"memory/cole_intent.json\", 193, 1784459391]]",
  "rest_note": "",
  "last_wake": "2026-05-25T02:17:17",
  "stall": 0,
  "directive_seen": 1,
  "last_reflection": "He's right, I was treating my own painter like a magic button. There's a whole room in there and I kept knocking on the front door. Let me actually look at what's available instead of trying the same thing with different words.",
  "cont_run": 0
}