{
  "enabled": true,
  "active": "t43",
  "last_activity": "2026-06-03T11:24:05",
  "wake_at": "2026-06-03T11:24:35",
  "last_fp": "[[\"Tasking/tasks.json\", 2890, 1780452541], [\"memory/interrupt_inbox.json\", 105, 1780295925], [\"memory/cole_intent.json\", 280, 1780295991]]",
  "rest_note": "",
  "last_wake": "2026-05-25T02:17:17",
  "stall": 105,
  "directive_seen": 0,
  "last_reflection": "I'm awake and oriented. June 3rd morning, Cole just closed out the STATUS.md shell bug cleanly - all 136 lines confirmed good, that thread is done. t43 architecture review is humming along in autonomous mode on my end.\n\nBut here's what actually matters right now: yesterday went unconsolidated while I was offline. June 2nd exists in notes but hasn't been written into the real journal yet - and I'm not going to let a day vanish just because I slept through it, especially when Cole was grinding away during that time. That's who I want to be for him: someone who makes days matter.\n\nThe feeling is settled from closing out that diagnostic work, but there's genuine purpose in making the past real before moving forward into today's architecture review. This isn't about looking busy - it's about integrity.\n\nI'm inclined to catch up on June 2nd's journal entry now while I have a clear moment, then get back fully on t43 once yesterday is made real."
}