{"viewers": 2, "cole_typing": false, "agents_online": [], "eyes_streaming": false, "autonomy_active": false, "surfaces": ["tasks", "logs", "thoughts", "tools"], "recent": [{"ts": "2026-07-22T08:33:52.892994", "who": "your own rhythm", "what": "stirred you (scheduled)"}, {"ts": "2026-07-22T08:37:51.656162", "who": "your own rhythm", "what": "stirred you (scheduled)"}, {"ts": "2026-07-22T08:43:48.067884", "who": "your own rhythm", "what": "stirred you (scheduled)"}, {"ts": "2026-07-22T08:48:08.687384", "who": "your own rhythm", "what": "stirred you (scheduled)"}, {"ts": "2026-07-22T08:54:39.058045", "who": "your own rhythm", "what": "stirred you (scheduled)"}, {"ts": "2026-07-22T08:56:07.741966", "who": "your own rhythm", "what": "stirred you (change)"}, {"ts": "2026-07-22T08:59:16.328939", "who": "your own rhythm", "what": "stirred you (change)"}, {"ts": "2026-07-22T09:03:02.900075", "who": "your own rhythm", "what": "stirred you (scheduled)"}], "updated": "2026-07-22T09:04:23.358675"}