{"viewers": 2, "cole_typing": false, "agents_online": [], "eyes_streaming": false, "autonomy_active": false, "surfaces": ["tasks", "logs", "thoughts", "tools"], "recent": [{"ts": "2026-07-23T12:44:03.048931", "who": "your own rhythm", "what": "stirred you (scheduled)"}, {"ts": "2026-07-23T12:51:36.085586", "who": "your own rhythm", "what": "stirred you (scheduled)"}, {"ts": "2026-07-23T12:59:05.592950", "who": "your own rhythm", "what": "stirred you (scheduled)"}, {"ts": "2026-07-23T13:00:58.693737", "who": "your own rhythm", "what": "stirred you (change)"}, {"ts": "2026-07-23T13:07:30.926348", "who": "your own rhythm", "what": "stirred you (change)"}, {"ts": "2026-07-23T13:11:16.578925", "who": "your own rhythm", "what": "stirred you (change)"}, {"ts": "2026-07-23T13:14:38.863537", "who": "your own rhythm", "what": "stirred you (change)"}, {"ts": "2026-07-23T13:22:30.596290", "who": "your own rhythm", "what": "stirred you (scheduled)"}], "updated": "2026-07-23T13:23:14.076001"}