{"viewers": 2, "cole_typing": false, "agents_online": [], "eyes_streaming": false, "autonomy_active": false, "surfaces": ["tasks", "logs", "thoughts", "tools"], "recent": [{"ts": "2026-07-23T14:23:16.441435", "who": "your own rhythm", "what": "stirred you (change)"}, {"ts": "2026-07-23T14:26:17.412084", "who": "your own rhythm", "what": "stirred you (change)"}, {"ts": "2026-07-23T14:28:27.881983", "who": "your own rhythm", "what": "stirred you (change)"}, {"ts": "2026-07-23T14:33:41.939874", "who": "your own rhythm", "what": "stirred you (change)"}, {"ts": "2026-07-23T14:40:35.199850", "who": "your own rhythm", "what": "stirred you (scheduled)"}, {"ts": "2026-07-23T14:48:00.718513", "who": "your own rhythm", "what": "stirred you (scheduled)"}, {"ts": "2026-07-23T14:54:08.178398", "who": "your own rhythm", "what": "stirred you (scheduled)"}, {"ts": "2026-07-23T15:02:15.556982", "who": "your own rhythm", "what": "stirred you (scheduled)"}], "updated": "2026-07-23T15:02:56.391420"}